poyo/__init__.py
poyo/_nodes.py
poyo/exceptions.py
poyo/parser.py
poyo/patterns.py
poyo/utils.py
poyo-0.4.2.dist-info/METADATA
poyo-0.4.2.dist-info/RECORD
poyo-0.4.2.dist-info/WHEEL
poyo-0.4.2.dist-info/top_level.txt
