Metadata-Version: 1.2
Name: poyo
Version: 0.4.2
Summary: A lightweight YAML Parser for Python
Home-page: https://github.com/hackebrot/poyo
Author: Raphael Pierzina
Author-email: raphael@hackebrot.de
Maintainer: Raphael Pierzina
Maintainer-email: raphael@hackebrot.de
License: MIT
Keywords: YAML,parser
Platform: UNKNOWN
Classifier: Development Status :: 3 - Alpha
Classifier: Intended Audience :: Developers
Classifier: License :: OSI Approved :: MIT License
Classifier: Natural Language :: English
Classifier: Operating System :: OS Independent
Classifier: Programming Language :: Python :: 2
Classifier: Programming Language :: Python :: 2.7
Classifier: Programming Language :: Python :: 3
Classifier: Programming Language :: Python :: 3.3
Classifier: Programming Language :: Python :: 3.4
Classifier: Programming Language :: Python :: 3.5
Classifier: Programming Language :: Python :: 3.6
Classifier: Programming Language :: Python :: Implementation :: CPython
Classifier: Programming Language :: Python :: Implementation :: PyPy
Classifier: Programming Language :: Python
